msgkit/__init__.py
msgkit/errorlog.py
msgkit/logging.py
msgkit/myfunctions.py
msgkit-0.1.6.dist-info/LICENSE.txt
msgkit-0.1.6.dist-info/METADATA
msgkit-0.1.6.dist-info/WHEEL
msgkit-0.1.6.dist-info/top_level.txt
msgkit-0.1.6.dist-info/RECORD
