Metadata-Version: 2.1
Name: msgkit
Version: 0.1.6
Summary: A Python library that is used for logging informative causes/solutions for given errors.
Home-page: https://github.com/JackScallan02/msgkit
Author: Jack Scallan
Author-email: jack.gregory.scallan@gmail.com
License: MIT
Download-URL: https://github.com/JackScallan02/msgkit/archive/refs/tags/v_01.6.tar.gz
Keywords: LOGGING,LOG,LOGS,ERROR,ERRORS
Platform: UNKNOWN
Classifier: Development Status :: 3 - Alpha
Classifier: Intended Audience :: Developers
Classifier: Topic :: Software Development :: Build Tools
Classifier: License :: OSI Approved :: MIT License
Classifier: Programming Language :: Python :: 3
Classifier: Programming Language :: Python :: 3.4
Classifier: Programming Language :: Python :: 3.5
Classifier: Programming Language :: Python :: 3.6
Classifier: Programming Language :: Python :: 3.7
